debuglogger/__init__.py
debuglogger-2.1.8.dist-info/LICENSE
debuglogger-2.1.8.dist-info/METADATA
debuglogger-2.1.8.dist-info/WHEEL
debuglogger-2.1.8.dist-info/top_level.txt
debuglogger-2.1.8.dist-info/RECORD
